wallman/__init__.py
wallman/__main__.py
wallman/main.py
wallman/wallman_classes.py
wallman/wallman_lib.py
wallman/wallman_systray.py
wallman-1.5.2.8.dist-info/LICENSE
wallman-1.5.2.8.dist-info/METADATA
wallman-1.5.2.8.dist-info/WHEEL
wallman-1.5.2.8.dist-info/entry_points.txt
wallman-1.5.2.8.dist-info/top_level.txt
wallman-1.5.2.8.dist-info/RECORD
